aipr/__init__.py
aipr/commit.py
aipr/main.py
aipr/providers.py
aipr/prompts/__init__.py
aipr/prompts/commit.xml
aipr/prompts/meta.xml
aipr/prompts/prompts.py
pr_generator_agent-1.5.0.dist-info/METADATA
pr_generator_agent-1.5.0.dist-info/WHEEL
pr_generator_agent-1.5.0.dist-info/entry_points.txt
pr_generator_agent-1.5.0.dist-info/licenses/LICENSE
pr_generator_agent-1.5.0.dist-info/RECORD
