Metadata-Version: 2.4
Name: pr-generator-agent
Version: 1.5.0
Summary: AI-powered Pull Request Description Generator
Project-URL: Repository, https://github.com/danielscholl/mr-generator-agent
Author-email: Daniel Scholl <daniel.scholl@microsoft.com>
License: MIT
License-File: LICENSE
Requires-Python: >=3.11
Requires-Dist: anthropic>=0.18.1
Requires-Dist: gitpython>=3.1.42
Requires-Dist: google-generativeai>=0.4.0
Requires-Dist: openai>=1.12.0
Requires-Dist: tiktoken>=0.6.0
Provides-Extra: dev
Requires-Dist: bandit[toml]>=1.7.5; extra == 'dev'
Requires-Dist: black>=24.2.0; extra == 'dev'
Requires-Dist: build>=1.0.3; extra == 'dev'
Requires-Dist: colorama>=0.4.6; extra == 'dev'
Requires-Dist: flake8-bugbear>=24.0.0; extra == 'dev'
Requires-Dist: flake8-comprehensions>=3.14.0; extra == 'dev'
Requires-Dist: flake8-docstrings>=1.7.0; extra == 'dev'
Requires-Dist: flake8-simplify>=0.21.0; extra == 'dev'
Requires-Dist: flake8>=7.0.0; extra == 'dev'
Requires-Dist: isort>=5.13.2; extra == 'dev'
Requires-Dist: mypy>=1.8.0; extra == 'dev'
Requires-Dist: pip-audit>=2.6.0; extra == 'dev'
Requires-Dist: pre-commit>=3.5.0; extra == 'dev'
Requires-Dist: pytest-cov>=4.1.0; extra == 'dev'
Requires-Dist: pytest>=8.0.2; extra == 'dev'
Requires-Dist: safety>=3.0.0; extra == 'dev'
Requires-Dist: types-requests>=2.31.0; extra == 'dev'
